{
    "start_epoch": 40,
    "parameter_changes":{
        "0": 44,
        "1": 155381,
        "2": 90112,
        "3": 16384,
        "4": 1100,
        "5": 2000000,
        "6": 370000000,
        "7": 18,
        "8": 500,
        "9": [3, 10],
        "10": [3, 1000],
        "11": [2, 10],
        "16": 340000000,
        "17": 4310,
        "18": {
        },
        "19": {
            "mem_price":  [577,10000],
            "step_price": [721,10000000]
        },
        "20": {
            "mem": 14000000,
            "steps": 10000000000

        },
        "21": {
            "mem": 62000000,
            "steps": 20000000000

        },
        "22": 5000,
        "23": 150,
        "24": 20,
        "25": {
        },
        "26": {
        },
        "27": 8,
        "28": 155,
        "29": 13,
        "30": 150000000000,
        "31": 50000,
        "32": 25,
        "33": 250
    }
}